flask_crud_generator/__init__.py
flask_crud_generator/generator.py
tests/__init__.py
tests/conftest.py
tests/models.py
tests/test_generator.py
flask_crud_generator-0.2.0.dist-info/LICENSE
flask_crud_generator-0.2.0.dist-info/METADATA
flask_crud_generator-0.2.0.dist-info/WHEEL
flask_crud_generator-0.2.0.dist-info/top_level.txt
flask_crud_generator-0.2.0.dist-info/RECORD
