Metadata-Version: 2.1
Name: flask_crud_generator
Version: 0.2.0
Summary: A Flask extension to generate CRUD routes based on models.
Home-page: https://github.com/UltraViolet33/flask_crud_generator
Author: Ultraviolet33
Classifier: Programming Language :: Python :: 3
Classifier: License :: OSI Approved :: MIT License
Classifier: Operating System :: OS Independent
Requires-Python: >=3.6
License-File: LICENSE
Requires-Dist: Flask
Requires-Dist: Flask-SQLAlchemy
